{
    "id": 7934,
    "name": "Revenant cyclops",
    "last_updated": "2024-06-25",
    "incomplete": true,
    "members": true,
    "release_date": "2017-11-23",
    "combat_level": 82,
    "size": 3,
    "hitpoints": 110,
    "max_hit": 16,
    "attack_type": [
        "crush",
        "ranged",
        "magic"
    ],
    "attack_speed": 6,
    "aggressive": true,
    "poisonous": false,
    "venomous": false,
    "immune_poison": false,
    "immune_venom": false,
    "attributes": [
        "spectral",
        "undead"
    ],
    "category": [
        "revenants",
        "ghosts"
    ],
    "slayer_monster": true,
    "slayer_level": 1,
    "slayer_xp": 119.0,
    "slayer_masters": [
        "turael",
        "spria",
        "krystilia",
        "mazchna"
    ],
    "duplicate": false,
    "examine": "The ghost of a cyclops slain long ago.",
    "wiki_name": "Revenant cyclops",
    "wiki_url": "https://oldschool.runescape.wiki/w/Revenant_cyclops",
    "attack_level": 60,
    "strength_level": 73,
    "defence_level": 49,
    "magic_level": 65,
    "ranged_level": 70,
    "attack_bonus": 53,
    "strength_bonus": 64,
    "attack_magic": 0,
    "magic_bonus": 0,
    "attack_ranged": 0,
    "ranged_bonus": 0,
    "defence_stab": 140,
    "defence_slash": 130,
    "defence_crush": 135,
    "defence_magic": 10,
    "defence_ranged": 135,
    "drops": []
}