{
    "itemId": 1937,
    "itemName": "Jug of water",
    "examine": "It's full of water.",
    "weight": 1.0,
    "buyLimit": 13000,
    "itemCreation": [
        {
            "ticks": 1,
            "materials": [
                {
                    "name": "Jug",
                    "quantity": 1
                }
            ],
            "facilities": "Water",
            "members": false,
            "output": {
                "quantity": 1,
                "name": "Jug of water"
            }
        }
    ]
}