{
    "itemId": 25660,
    "itemName": "Cavefish",
    "examine": "This should be offered up at the altar.",
    "weight": 0.12,
    "itemCreation": [
        {
            "ticks": 2,
            "materials": [
                {
                    "name": "Raw cavefish",
                    "quantity": 1
                }
            ],
            "facilities": "Preparation Table",
            "tools": "Knife",
            "skills": [
                {
                    "experience": 23.0,
                    "level": 20,
                    "name": "Cooking",
                    "boostable": true
                }
            ],
            "members": false,
            "output": {
                "quantity": 1,
                "name": "Cavefish"
            }
        }
    ]
}