{
    "itemId": 28202,
    "itemName": "Steel felling axe",
    "examine": "A woodcutter's felling axe.",
    "weight": 1.814,
    "itemCreation": [
        {
            "ticks": 3,
            "materials": [
                {
                    "name": "Felling axe handle",
                    "quantity": 1
                },
                {
                    "name": "Steel axe",
                    "quantity": 1
                }
            ],
            "facilities": "Anvil",
            "tools": "Hammer",
            "skills": [
                {
                    "experience": 5.0,
                    "level": 6,
                    "name": "Smithing",
                    "boostable": true
                }
            ],
            "output": {
                "quantity": 1,
                "name": "Steel felling axe"
            }
        }
    ],
    "equipment": {
        "slot": "WEAPON",
        "stabAttackBonus": -3,
        "slashAttackBonus": 12,
        "crushAttackBonus": 9,
        "slashDefenceBonus": 1,
        "strengthBonus": 14,
        "attackDistance": 1,
        "attackSpeed": 7,
        "weaponType": "AXE"
    }
}