{
    "npcIds": [
        11942
    ],
    "name": "Guard",
    "hitpoints": 22,
    "combatLevel": 21,
    "attackSpeed": 4,
    "attackTypes": [
        "STAB"
    ],
    "maxHits": [
        3
    ],
    "size": 1,
    "attackLevel": 19,
    "strengthLevel": 18,
    "defenceLevel": 14,
    "magicLevel": 1,
    "rangedLevel": 1,
    "attackBonus": 4,
    "strengthBonus": 5,
    "stabDefenceBonus": 18,
    "slashDefenceBonus": 25,
    "crushDefenceBonus": 19,
    "magicDefenceBonus": -4,
    "rangedDefenceBonus": 20
}