{
    "npcId": 12458,
    "name": "Sulphur Lizard",
    "hitpoints": 500,
    "combatLevel": 257,
    "attackSpeed": 4,
    "attackStyles": [
        "CRUSH"
    ],
    "maxHits": [
        21
    ],
    "slayerCategory": "Lizards",
    "assignedBy": [
        "MAZCHNA",
        "VANNAKA",
        "CHAELDAR",
        "SPRIA"
    ],
    "size": 2,
    "attackLevel": 150,
    "strengthLevel": 200,
    "defenceLevel": 75,
    "magicLevel": 1,
    "rangedLevel": 1,
    "stabDefenceBonus": 15,
    "slashDefenceBonus": 25,
    "crushDefenceBonus": 25,
    "rangeDefenceBonus": 15,
    "lightRangeDefenceBonus": 15,
    "standardRangeDefenceBonus": 15,
    "heavyRangeDefenceBonus": 15,
    "immuneToPoison": false,
    "immuneToVenom": false
}