{
    "npcIds": [
        2145
    ],
    "name": "Undead Druid",
    "hitpoints": 140,
    "combatLevel": 105,
    "attackSpeed": 4,
    "attackStyles": [
        "MELEE",
        "MAGIC"
    ],
    "maxHits": [
        22,
        11
    ],
    "monsterAttribute": "undead",
    "slayerCategory": "Zombies",
    "assignedBy": [
        "MAZCHNA",
        "SPRIA"
    ],
    "slayerExperience": 147.0,
    "size": 1,
    "attackLevel": 60,
    "strengthLevel": 50,
    "defenceLevel": 60,
    "magicLevel": 115,
    "attackBonus": 50,
    "strengthBonus": 50,
    "magicAttackBonus": 100,
    "magicDamageBonus": 50,
    "stabDefenceBonus": 40,
    "slashDefenceBonus": 30,
    "crushDefenceBonus": 80,
    "magicDefenceBonus": 140,
    "rangedDefenceBonus": 40
}