{
    "npcId": 2999,
    "name": "Tortured soul",
    "hitpoints": 51,
    "combatLevel": 59,
    "attackSpeed": 4,
    "attackStyles": [
        "CRUSH"
    ],
    "maxHits": [
        7
    ],
    "monsterAttribute": "spectral",
    "slayerCategory": "Ghosts",
    "assignedBy": [
        "MAZCHNA",
        "SPRIA"
    ],
    "slayerExperience": 51.0,
    "size": 1,
    "attackLevel": 52,
    "strengthLevel": 62,
    "defenceLevel": 38,
    "magicLevel": 1,
    "rangedLevel": 1,
    "immuneToPoison": false,
    "immuneToVenom": false
}