{
    "npcId": 6294,
    "name": "Ice Troll King (hard)",
    "hitpoints": 240,
    "combatLevel": 213,
    "attackSpeed": 4,
    "attackStyles": [
        "CRUSH"
    ],
    "maxHits": [
        40
    ],
    "slayerCategory": "Trolls",
    "assignedBy": [
        "VANNAKA",
        "CHAELDAR",
        "DURADEL",
        "NIEVE"
    ],
    "slayerExperience": 287.0,
    "size": 2,
    "attackLevel": 200,
    "strengthLevel": 200,
    "defenceLevel": 80,
    "magicLevel": 1,
    "rangedLevel": 1,
    "attackBonus": 60,
    "strengthBonus": 60,
    "stabDefenceBonus": 45,
    "slashDefenceBonus": 45,
    "crushDefenceBonus": 45,
    "magicDefenceBonus": 2000,
    "rangeDefenceBonus": 2000,
    "lightRangeDefenceBonus": 2000,
    "standardRangeDefenceBonus": 2000,
    "heavyRangeDefenceBonus": 2000,
    "immuneToPoison": false,
    "immuneToVenom": false
}