{
    "npcIds": [
        8069
    ],
    "name": "Zombie",
    "hitpoints": 54,
    "combatLevel": 132,
    "attackSpeed": 5,
    "attackStyles": [
        "MAGIC"
    ],
    "maxHits": [
        19
    ],
    "monsterAttribute": "undead",
    "slayerCategory": "Zombies",
    "assignedBy": [
        "MAZCHNA",
        "SPRIA"
    ],
    "size": 1,
    "attackLevel": 160,
    "strengthLevel": 1,
    "defenceLevel": 62,
    "magicLevel": 180,
    "rangedLevel": 1,
    "magicAttackBonus": 20,
    "stabDefenceBonus": 35,
    "slashDefenceBonus": 30,
    "crushDefenceBonus": 35,
    "magicDefenceBonus": 20,
    "rangedDefenceBonus": 10
}