{
    "npcIds": [
        8715
    ],
    "name": "Spawn of Sarachnis",
    "hitpoints": 30,
    "combatLevel": 68,
    "attackSpeed": 4,
    "attackTypes": [
        "MAGIC"
    ],
    "maxHits": [
        11
    ],
    "slayerCategory": "Spiders",
    "assignedBy": [
        "SPRIA"
    ],
    "slayerExperience": 30.0,
    "size": 2,
    "attackLevel": 10,
    "strengthLevel": 10,
    "defenceLevel": 50,
    "magicLevel": 100,
    "rangedLevel": 1,
    "stabDefenceBonus": 50,
    "slashDefenceBonus": 50,
    "crushDefenceBonus": 50,
    "magicDefenceBonus": 150
}