{
    "npcIds": [
        2862,
        2863,
        2864
    ],
    "name": "Giant rat",
    "searchName": "Giant rat#Level 6",
    "hitpoints": 10,
    "combatLevel": 6,
    "attackSpeed": 4,
    "attackStyles": [
        "STAB"
    ],
    "maxHits": [
        1
    ],
    "monsterAttribute": "rat",
    "slayerCategory": "Rats",
    "assignedBy": [
        "SPRIA"
    ],
    "slayerExperience": 10.0,
    "size": 2,
    "attackLevel": 6,
    "strengthLevel": 5,
    "defenceLevel": 2,
    "magicLevel": 1,
    "rangedLevel": 1
}