{
    "npcIds": [
        7550
    ],
    "name": "Great Olm (Right claw)",
    "hitpoints": 600,
    "combatLevel": 549,
    "attackSpeed": 4,
    "maxHits": [
        0
    ],
    "monsterAttribute": "dragon",
    "size": 5,
    "attackLevel": 250,
    "strengthLevel": 250,
    "defenceLevel": 175,
    "magicLevel": 87,
    "rangedLevel": 250,
    "magicAttackBonus": 60,
    "rangeAttackBonus": 60,
    "stabDefenceBonus": 200,
    "slashDefenceBonus": 200,
    "crushDefenceBonus": 200,
    "magicDefenceBonus": 50,
    "rangedDefenceBonus": 200,
    "immuneToPoison": true,
    "immuneToVenom": true
}