{
    "npcIds": [
        8710,
        8709
    ],
    "name": "Shaeded Beast",
    "hitpoints": 210,
    "combatLevel": 186,
    "attackSpeed": 4,
    "attackTypes": [
        "MAGIC"
    ],
    "maxHits": [
        30
    ],
    "size": 3,
    "attackLevel": 50,
    "strengthLevel": 80,
    "defenceLevel": 50,
    "magicLevel": 250,
    "rangedLevel": 1,
    "magicDamageBonus": 10,
    "stabDefenceBonus": 50,
    "slashDefenceBonus": 30,
    "crushDefenceBonus": 100,
    "magicDefenceBonus": 150,
    "rangedDefenceBonus": 50
}