{
    "npcIds": [
        6319
    ],
    "name": "Tree spirit (hard)",
    "searchName": "Tree spirit (Lost City)#Hard",
    "hitpoints": 187,
    "combatLevel": 199,
    "attackSpeed": 4,
    "attackStyles": [
        "CRUSH"
    ],
    "maxHits": [
        22
    ],
    "monsterAttribute": "undead",
    "slayerCategory": "Ghosts",
    "assignedBy": [
        "MAZCHNA",
        "SPRIA"
    ],
    "size": 1,
    "attackLevel": 200,
    "strengthLevel": 209,
    "defenceLevel": 80,
    "magicLevel": 1,
    "rangedLevel": 1
}